IVIMNET/__init__.py
IVIMNET/deep.py
IVIMNET/fitting_algorithms.py
IVIMNET/simulations.py
ivimnet-0.1.1.dist-info/licenses/LICENSE
ivimnet-0.1.1.dist-info/METADATA
ivimnet-0.1.1.dist-info/WHEEL
ivimnet-0.1.1.dist-info/top_level.txt
ivimnet-0.1.1.dist-info/RECORD
